moonframe/__init__.py
moonframe/app_builder.py
moonframe/application.py
moonframe/cli.py
moonframe/static/.DS_Store
moonframe/static/circular_packing/color.js
moonframe/static/circular_packing/main.js
moonframe/static/circular_packing/mouseevent.js
moonframe/static/circular_packing/search.js
moonframe/static/circular_packing/style.css
moonframe/static/circular_packing/worst_performers.js
moonframe/static/circular_packing/zoom.js
moonframe/static/general/color_legend_cat.js
moonframe/static/general/color_legend_cont.js
moonframe/static/general/general_style.css
moonframe/static/general/palettes.js
moonframe/static/general/MMAP/card.js
moonframe/static/general/MMAP/color_constrast.js
moonframe/static/general/MMAP/color_palette_picker.js
moonframe/static/general/MMAP/color_scale.js
moonframe/static/general/MMAP/common_style.css
moonframe/static/general/MMAP/openCode.js
moonframe/static/general/MMAP/page.js
moonframe/static/network/clickevent.js
moonframe/static/network/color.js
moonframe/static/network/global.js
moonframe/static/network/hulls.js
moonframe/static/network/main.js
moonframe/static/network/mouseevent.js
moonframe/static/network/search.js
moonframe/static/network/size.js
moonframe/static/network/style.css
moonframe/templates/circular_packing.html
moonframe/templates/network.html
moonframe/templates/nobvisual.html
moonframe/templates/scatter.html
moonframe-0.7.0.dist-info/licenses/LICENSE.txt
moonframe-0.7.0.dist-info/METADATA
moonframe-0.7.0.dist-info/WHEEL
moonframe-0.7.0.dist-info/entry_points.txt
moonframe-0.7.0.dist-info/top_level.txt
moonframe-0.7.0.dist-info/RECORD
