Metadata-Version: 2.4
Name: moonframe
Version: 0.7.0
Summary: Simple and interactive plots using d3js
Author-email: CoopTeam-CERFACS <coop@cerfacs.fr>
License: Copyright (c) 2021 Cerfacs/COOP Team
Project-URL: Homepage, https://gitlab.com/cerfacs/moonframe
Project-URL: Documentation, https://gitlab.com/cerfacs/moonframe/-/tree/main/docs
Project-URL: Issues, https://gitlab.com/cerfacs/moonframe/-/issues
Project-URL: Changelog, https://gitlab.com/cerfacs/moonframe/-/blob/main/CHANGELOG.md
Keywords: data visualization,d3js,plot,charts,graph,scatter
Classifier: Programming Language :: Python :: 3.7
Classifier: Programming Language :: Python :: 3.8
Classifier: Programming Language :: Python :: 3.9
Classifier: Programming Language :: Python :: 3.10
Classifier: Programming Language :: Python :: 3.11
Classifier: Programming Language :: Python :: 3.12
Classifier: Programming Language :: Python :: 3.13
Classifier: Intended Audience :: Developers
Classifier: Intended Audience :: Science/Research
Classifier: Topic :: Scientific/Engineering :: Visualization
Requires-Python: >=3.7
License-File: LICENSE.txt
Requires-Dist: click
Requires-Dist: flask
Requires-Dist: waitress
Requires-Dist: loguru
Provides-Extra: tests
Requires-Dist: pytest; extra == "tests"
Requires-Dist: pytest-coverage; extra == "tests"
Requires-Dist: pytest-datadir; extra == "tests"
Requires-Dist: pytest-allclose; extra == "tests"
Dynamic: license-file
